Workbook

Sheet Project Brief
A1: Lesson 10 — Practical Merchandise Planning Project
A3: Objective | B3: Build an end-to-end merchandise plan using the concepts from Lessons 1–9.
A5: Annual Sales Target | B5: 100000000
A6: Gross Margin % | B6: 0.6
A7: Opening Inventory | B7: 25000000
A8: Desired Closing Inventory | B8: 30000000
A9: Planning Horizon (weeks) | B9: 26

Sheet Sales Plan
A1: Sales Plan
A3: Month | B3: Plan Sales ₹ | C3: Phasing % | D3: Actual Sales ₹ | E3: Achievement % | F3: Variance ₹ | G3: ASP ₹ | H3: Units
A4: Apr | B4: ='Project Brief'!$B$5*C4 -> 7000000 | C4: 0.07 | E4: =IFERROR(D4/B4,0) -> 0 | F4: =D4-B4 -> -7000000 | G4: 8000 | H4: =IFERROR(D4/G4,0) -> 0
A5: May | B5: ='Project Brief'!$B$5*C5 -> 7000000 | C5: 0.07 | E5: =IFERROR(D5/B5,0) -> 0 | F5: =D5-B5 -> -7000000 | G5: 8000 | H5: =IFERROR(D5/G5,0) -> 0
A6: Jun | B6: ='Project Brief'!$B$5*C6 -> 7500000 | C6: 0.075 | E6: =IFERROR(D6/B6,0) -> 0 | F6: =D6-B6 -> -7500000 | G6: 8000 | H6: =IFERROR(D6/G6,0) -> 0
A7: Jul | B7: ='Project Brief'!$B$5*C7 -> 7500000 | C7: 0.075 | E7: =IFERROR(D7/B7,0) -> 0 | F7: =D7-B7 -> -7500000 | G7: 8000 | H7: =IFERROR(D7/G7,0) -> 0
A8: Aug | B8: ='Project Brief'!$B$5*C8 -> 8000000 | C8: 0.08 | E8: =IFERROR(D8/B8,0) -> 0 | F8: =D8-B8 -> -8000000 | G8: 8000 | H8: =IFERROR(D8/G8,0) -> 0
A9: Sep | B9: ='Project Brief'!$B$5*C9 -> 8000000 | C9: 0.08 | E9: =IFERROR(D9/B9,0) -> 0 | F9: =D9-B9 -> -8000000 | G9: 8000 | H9: =IFERROR(D9/G9,0) -> 0
A10: Oct | B10: ='Project Brief'!$B$5*C10 -> 8500000 | C10: 0.085 | E10: =IFERROR(D10/B10,0) -> 0 | F10: =D10-B10 -> -8500000 | G10: 8000 | H10: =IFERROR(D10/G10,0) -> 0
A11: Nov | B11: ='Project Brief'!$B$5*C11 -> 9000000 | C11: 0.09 | E11: =IFERROR(D11/B11,0) -> 0 | F11: =D11-B11 -> -9000000 | G11: 8000 | H11: =IFERROR(D11/G11,0) -> 0
A12: Dec | B12: ='Project Brief'!$B$5*C12 -> 10000000 | C12: 0.1 | E12: =IFERROR(D12/B12,0) -> 0 | F12: =D12-B12 -> -10000000 | G12: 8000 | H12: =IFERROR(D12/G12,0) -> 0
A13: Jan | B13: ='Project Brief'!$B$5*C13 -> 9000000 | C13: 0.09 | E13: =IFERROR(D13/B13,0) -> 0 | F13: =D13-B13 -> -9000000 | G13: 8000 | H13: =IFERROR(D13/G13,0) -> 0
A14: Feb | B14: ='Project Brief'!$B$5*C14 -> 8500000 | C14: 0.085 | E14: =IFERROR(D14/B14,0) -> 0 | F14: =D14-B14 -> -8500000 | G14: 8000 | H14: =IFERROR(D14/G14,0) -> 0
A15: Mar | B15: ='Project Brief'!$B$5*C15 -> 8500000 | C15: 0.085 | E15: =IFERROR(D15/B15,0) -> 0 | F15: =D15-B15 -> -8500000 | G15: 8000 | H15: =IFERROR(D15/G15,0) -> 0
A16: TOTAL | B16: =SUM(B4:B15) -> 98500000 | D16: =SUM(D4:D15) -> 0 | F16: =SUM(F4:F15) -> -98500000 | H16: =SUM(H4:H15) -> 0

Sheet Category Plan
A1: Category Plan
A3: Category | B3: Sales Mix % | C3: Sales Plan ₹ | D3: ASP ₹ | E3: Units Plan | F3: Opening Stock ₹ | G3: Closing Stock Target ₹ | H3: Action / Comment
A4: Shirts | B4: 0.3 | C4: ='Project Brief'!$B$5*B4 -> 30000000 | D4: 4500 | E4: =IFERROR(C4/D4,0) -> 6666.6667 | F4: ='Project Brief'!$B$7*B4 -> 7500000 | G4: ='Project Brief'!$B$8*B4 -> 9000000 | H4: Review
A5: Polos | B5: 0.2 | C5: ='Project Brief'!$B$5*B5 -> 20000000 | D5: 3000 | E5: =IFERROR(C5/D5,0) -> 6666.6667 | F5: ='Project Brief'!$B$7*B5 -> 5000000 | G5: ='Project Brief'!$B$8*B5 -> 6000000 | H5: Review
A6: T-shirts | B6: 0.2 | C6: ='Project Brief'!$B$5*B6 -> 20000000 | D6: 2200 | E6: =IFERROR(C6/D6,0) -> 9090.9091 | F6: ='Project Brief'!$B$7*B6 -> 5000000 | G6: ='Project Brief'!$B$8*B6 -> 6000000 | H6: Review
A7: Trousers | B7: 0.15 | C7: ='Project Brief'!$B$5*B7 -> 15000000 | D7: 5000 | E7: =IFERROR(C7/D7,0) -> 3000 | F7: ='Project Brief'!$B$7*B7 -> 3750000 | G7: ='Project Brief'!$B$8*B7 -> 4500000 | H7: Review
A8: Denim | B8: 0.15 | C8: ='Project Brief'!$B$5*B8 -> 15000000 | D8: 6000 | E8: =IFERROR(C8/D8,0) -> 2500 | F8: ='Project Brief'!$B$7*B8 -> 3750000 | G8: ='Project Brief'!$B$8*B8 -> 4500000 | H8: Review

Sheet 26 Week WSSI
A1: 26-Week WSSI
A3: Week | B3: Phase | C3: Opening Stock ₹ | D3: Sales Plan ₹ | E3: Receipts Plan ₹ | F3: Closing Stock Plan ₹ | G3: Actual Sales ₹ | H3: Actual Receipts ₹ | I3: Actual Closing ₹ | J3: WOS | K3: Action
A4: 1 | B4: Normal | C4: ='Project Brief'!$B$7 -> 25000000 | D4: ='Project Brief'!$B$5/26 -> 3846153.8 | E4: =D4 -> 3846153.8 | F4: =C4+E4-D4 -> 25000000 | J4: =IFERROR(I4/(G4),0) -> 0 | K4: Review
A5: 2 | B5: Normal | C5: =F4 -> 25000000 | D5: ='Project Brief'!$B$5/26 -> 3846153.8 | E5: =D5 -> 3846153.8 | F5: =C5+E5-D5 -> 25000000 | J5: =IFERROR(I5/(G5),0) -> 0 | K5: Review
A6: 3 | B6: Normal | C6: =F5 -> 25000000 | D6: ='Project Brief'!$B$5/26 -> 3846153.8 | E6: =D6 -> 3846153.8 | F6: =C6+E6-D6 -> 25000000 | J6: =IFERROR(I6/(G6),0) -> 0 | K6: Review
A7: 4 | B7: Normal | C7: =F6 -> 25000000 | D7: ='Project Brief'!$B$5/26 -> 3846153.8 | E7: =D7 -> 3846153.8 | F7: =C7+E7-D7 -> 25000000 | J7: =IFERROR(I7/(G7),0) -> 0 | K7: Review
A8: 5 | B8: Normal | C8: =F7 -> 25000000 | D8: ='Project Brief'!$B$5/26 -> 3846153.8 | E8: =D8 -> 3846153.8 | F8: =C8+E8-D8 -> 25000000 | J8: =IFERROR(I8/(G8),0) -> 0 | K8: Review
A9: 6 | B9: Normal | C9: =F8 -> 25000000 | D9: ='Project Brief'!$B$5/26 -> 3846153.8 | E9: =D9 -> 3846153.8 | F9: =C9+E9-D9 -> 25000000 | J9: =IFERROR(I9/(G9),0) -> 0 | K9: Review
A10: 7 | B10: Normal | C10: =F9 -> 25000000 | D10: ='Project Brief'!$B$5/26 -> 3846153.8 | E10: =D10 -> 3846153.8 | F10: =C10+E10-D10 -> 25000000 | J10: =IFERROR(I10/(G10),0) -> 0 | K10: Review
A11: 8 | B11: Normal | C11: =F10 -> 25000000 | D11: ='Project Brief'!$B$5/26 -> 3846153.8 | E11: =D11 -> 3846153.8 | F11: =C11+E11-D11 -> 25000000 | J11: =IFERROR(I11/(G11),0) -> 0 | K11: Review
A12: 9 | B12: Normal | C12: =F11 -> 25000000 | D12: ='Project Brief'!$B$5/26 -> 3846153.8 | E12: =D12 -> 3846153.8 | F12: =C12+E12-D12 -> 25000000 | J12: =IFERROR(I12/(G12),0) -> 0 | K12: Review
A13: 10 | B13: Normal | C13: =F12 -> 25000000 | D13: ='Project Brief'!$B$5/26 -> 3846153.8 | E13: =D13 -> 3846153.8 | F13: =C13+E13-D13 -> 25000000 | J13: =IFERROR(I13/(G13),0) -> 0 | K13: Review
A14: 11 | B14: Normal | C14: =F13 -> 25000000 | D14: ='Project Brief'!$B$5/26 -> 3846153.8 | E14: =D14 -> 3846153.8 | F14: =C14+E14-D14 -> 25000000 | J14: =IFERROR(I14/(G14),0) -> 0 | K14: Review
A15: 12 | B15: Normal | C15: =F14 -> 25000000 | D15: ='Project Brief'!$B$5/26 -> 3846153.8 | E15: =D15 -> 3846153.8 | F15: =C15+E15-D15 -> 25000000 | J15: =IFERROR(I15/(G15),0) -> 0 | K15: Review
A16: 13 | B16: Normal | C16: =F15 -> 25000000 | D16: ='Project Brief'!$B$5/26 -> 3846153.8 | E16: =D16 -> 3846153.8 | F16: =C16+E16-D16 -> 25000000 | J16: =IFERROR(I16/(G16),0) -> 0 | K16: Review
... A29: 26 | B29: EOSS | C29: =F28 -> 25000000 | D29: ='Project Brief'!$B$5/26 -> 3846153.8 | E29: =D29 -> 3846153.8 | F29: =C29+E29-D29 -> 25000000 | J29: =IFERROR(I29/(G29),0) -> 0 | K29: Review

Sheet OTB
A1: Open to Buy (OTB)
A3: Month | B3: Planned Sales ₹ | C3: Desired Closing Stock ₹ | D3: Opening Stock ₹ | E3: Committed Receipts ₹ | F3: OTB Retail ₹ | G3: Cost-to-Retail % | H3: OTB Cost ₹ | I3: Actual Orders ₹ | J3: Remaining OTB ₹
A4: Apr | B4: ='Sales Plan'!B4 -> 7000000 | C4: 2500000 | D4: 2000000 | E4: 1000000 | F4: =B4+C4-D4-E4 -> 6500000 | G4: 0.3 | H4: =F4*G4 -> 1950000 | J4: =F4-I4 -> 6500000
A5: May | B5: ='Sales Plan'!B5 -> 7000000 | C5: 2500000 | D5: 2000000 | E5: 1000000 | F5: =B5+C5-D5-E5 -> 6500000 | G5: 0.3 | H5: =F5*G5 -> 1950000 | J5: =F5-I5 -> 6500000
A6: Jun | B6: ='Sales Plan'!B6 -> 7500000 | C6: 2500000 | D6: 2000000 | E6: 1000000 | F6: =B6+C6-D6-E6 -> 7000000 | G6: 0.3 | H6: =F6*G6 -> 2100000 | J6: =F6-I6 -> 7000000
A7: Jul | B7: ='Sales Plan'!B7 -> 7500000 | C7: 2500000 | D7: 2000000 | E7: 1000000 | F7: =B7+C7-D7-E7 -> 7000000 | G7: 0.3 | H7: =F7*G7 -> 2100000 | J7: =F7-I7 -> 7000000
A8: Aug | B8: ='Sales Plan'!B8 -> 8000000 | C8: 2500000 | D8: 2000000 | E8: 1000000 | F8: =B8+C8-D8-E8 -> 7500000 | G8: 0.3 | H8: =F8*G8 -> 2250000 | J8: =F8-I8 -> 7500000
A9: Sep | B9: ='Sales Plan'!B9 -> 8000000 | C9: 2500000 | D9: 2000000 | E9: 1000000 | F9: =B9+C9-D9-E9 -> 7500000 | G9: 0.3 | H9: =F9*G9 -> 2250000 | J9: =F9-I9 -> 7500000
A10: Oct | B10: ='Sales Plan'!B10 -> 8500000 | C10: 2500000 | D10: 2000000 | E10: 1000000 | F10: =B10+C10-D10-E10 -> 8000000 | G10: 0.3 | H10: =F10*G10 -> 2400000 | J10: =F10-I10 -> 8000000
A11: Nov | B11: ='Sales Plan'!B11 -> 9000000 | C11: 2500000 | D11: 2000000 | E11: 1000000 | F11: =B11+C11-D11-E11 -> 8500000 | G11: 0.3 | H11: =F11*G11 -> 2550000 | J11: =F11-I11 -> 8500000
A12: Dec | B12: ='Sales Plan'!B12 -> 10000000 | C12: 2500000 | D12: 2000000 | E12: 1000000 | F12: =B12+C12-D12-E12 -> 9500000 | G12: 0.3 | H12: =F12*G12 -> 2850000 | J12: =F12-I12 -> 9500000
A13: Jan | B13: ='Sales Plan'!B13 -> 9000000 | C13: 2500000 | D13: 2000000 | E13: 1000000 | F13: =B13+C13-D13-E13 -> 8500000 | G13: 0.3 | H13: =F13*G13 -> 2550000 | J13: =F13-I13 -> 8500000
A14: Feb | B14: ='Sales Plan'!B14 -> 8500000 | C14: 2500000 | D14: 2000000 | E14: 1000000 | F14: =B14+C14-D14-E14 -> 8000000 | G14: 0.3 | H14: =F14*G14 -> 2400000 | J14: =F14-I14 -> 8000000
A15: Mar | B15: ='Sales Plan'!B15 -> 8500000 | C15: 2500000 | D15: 2000000 | E15: 1000000 | F15: =B15+C15-D15-E15 -> 8000000 | G15: 0.3 | H15: =F15*G15 -> 2400000 | J15: =F15-I15 -> 8000000

Sheet ROS WOS
A1: ROS / WOS / Sell-Through
A3: Product | B3: Opening Units | C3: Receipts Units | D3: Units Sold | E3: ROS / Week | F3: Closing Units | G3: WOS | H3: Sell-Through % | I3: Action
A4: Formal Shirt | B4: 500 | C4: 300 | D4: 600 | E4: =D4/4 -> 150 | F4: =B4+C4-D4 -> 200 | G4: =IFERROR(F4/E4,0) -> 1.3333333 | H4: =IFERROR(D4/(B4+C4),0) -> 0.75 | I4: Review
A5: Casual Shirt | B5: 500 | C5: 300 | D5: 600 | E5: =D5/4 -> 150 | F5: =B5+C5-D5 -> 200 | G5: =IFERROR(F5/E5,0) -> 1.3333333 | H5: =IFERROR(D5/(B5+C5),0) -> 0.75 | I5: Review
A6: Polo | B6: 500 | C6: 300 | D6: 600 | E6: =D6/4 -> 150 | F6: =B6+C6-D6 -> 200 | G6: =IFERROR(F6/E6,0) -> 1.3333333 | H6: =IFERROR(D6/(B6+C6),0) -> 0.75 | I6: Review
A7: Graphic T-shirt | B7: 500 | C7: 300 | D7: 600 | E7: =D7/4 -> 150 | F7: =B7+C7-D7 -> 200 | G7: =IFERROR(F7/E7,0) -> 1.3333333 | H7: =IFERROR(D7/(B7+C7),0) -> 0.75 | I7: Review
A8: Basic T-shirt | B8: 500 | C8: 300 | D8: 600 | E8: =D8/4 -> 150 | F8: =B8+C8-D8 -> 200 | G8: =IFERROR(F8/E8,0) -> 1.3333333 | H8: =IFERROR(D8/(B8+C8),0) -> 0.75 | I8: Review
A9: Trouser | B9: 500 | C9: 300 | D9: 600 | E9: =D9/4 -> 150 | F9: =B9+C9-D9 -> 200 | G9: =IFERROR(F9/E9,0) -> 1.3333333 | H9: =IFERROR(D9/(B9+C9),0) -> 0.75 | I9: Review
A10: Chino | B10: 500 | C10: 300 | D10: 600 | E10: =D10/4 -> 150 | F10: =B10+C10-D10 -> 200 | G10: =IFERROR(F10/E10,0) -> 1.3333333 | H10: =IFERROR(D10/(B10+C10),0) -> 0.75 | I10: Review
A11: Denim | B11: 500 | C11: 300 | D11: 600 | E11: =D11/4 -> 150 | F11: =B11+C11-D11 -> 200 | G11: =IFERROR(F11/E11,0) -> 1.3333333 | H11: =IFERROR(D11/(B11+C11),0) -> 0.75 | I11: Review
A12: Jacket | B12: 500 | C12: 300 | D12: 600 | E12: =D12/4 -> 150 | F12: =B12+C12-D12 -> 200 | G12: =IFERROR(F12/E12,0) -> 1.3333333 | H12: =IFERROR(D12/(B12+C12),0) -> 0.75 | I12: Review
A13: Shacket | B13: 500 | C13: 300 | D13: 600 | E13: =D13/4 -> 150 | F13: =B13+C13-D13 -> 200 | G13: =IFERROR(F13/E13,0) -> 1.3333333 | H13: =IFERROR(D13/(B13+C13),0) -> 0.75 | I13: Review

Sheet Assortment
A1: Assortment Plan
A3: Category | B3: Sub-category | C3: Product / Option | D3: Role | E3: Colour | F3: Size | G3: Price ₹ | H3: Planned Options | I3: Planned Units | J3: Units / Option | K3: Sales Plan ₹ | L3: Action / Comment
A4: Shirts | B4: Formal | C4: Easy-Iron Shirt | D4: Core | E4: White | F4: M-L-XL | G4: 4500 | H4: 4 | I4: 400 | J4: =IFERROR(I4/H4,0) -> 100 | K4: =G4*I4 -> 1800000 | L4: Core depth
A5: Shirts | B5: Casual | C5: Oxford Shirt | D5: Core | E5: Blue | F5: M-L-XL | G5: 5000 | H5: 4 | I5: 320 | J5: =IFERROR(I5/H5,0) -> 80 | K5: =G5*I5 -> 1600000 | L5: Core depth
A6: Polos | B6: Basic | C6: Pique Polo | D6: Core | E6: Navy | F6: M-L-XL | G6: 3000 | H6: 3 | I6: 300 | J6: =IFERROR(I6/H6,0) -> 100 | K6: =G6*I6 -> 900000 | L6: Repeat
A7: T-shirts | B7: Basic | C7: Crew Neck | D7: Core | E7: White | F7: M-L-XL | G7: 2200 | H7: 3 | I7: 360 | J7: =IFERROR(I7/H7,0) -> 120 | K7: =G7*I7 -> 792000 | L7: Repeat
A8: Trousers | B8: Chino | C8: Slim Chino | D8: Core | E8: Beige | F8: 30-32-34-36 | G8: 5000 | H8: 3 | I8: 240 | J8: =IFERROR(I8/H8,0) -> 80 | K8: =G8*I8 -> 1200000 | L8: Size depth
A9: Denim | B9: Regular | C9: Regular Denim | D9: Core | E9: Indigo | F9: 30-32-34-36 | G9: 6000 | H9: 3 | I9: 180 | J9: =IFERROR(I9/H9,0) -> 60 | K9: =G9*I9 -> 1080000 | L9: Depth

Sheet Size Curve
A1: Size Curve
A3: Category | B3: XS % | C3: S % | D3: M % | E3: L % | F3: XL % | G3: XXL % | H3: Total Units | I3: XS Units | J3: S Units | K3: M Units | L3: L Units | M3: XL Units | N3: XXL Units
A4: T-shirt | B4: 0.05 | C4: 0.1 | D4: 0.25 | E4: 0.3 | F4: 0.22 | G4: 0.08 | H4: 1000 | I4: =H4*B4 -> 50 | J4: =H4*C4 -> 100 | K4: =H4*D4 -> 250 | L4: =H4*E4 -> 300 | M4: =H4*F4 -> 220 | N4: =H4*G4 -> 80
A5: Polo | B5: 0.03 | C5: 0.08 | D5: 0.27 | E5: 0.32 | F5: 0.22 | G5: 0.08 | H5: 800 | I5: =H5*B5 -> 24 | J5: =H5*C5 -> 64 | K5: =H5*D5 -> 216 | L5: =H5*E5 -> 256 | M5: =H5*F5 -> 176 | N5: =H5*G5 -> 64
A6: Shirt | B6: 0.02 | C6: 0.08 | D6: 0.28 | E6: 0.32 | F6: 0.22 | G6: 0.08 | H6: 900 | I6: =H6*B6 -> 18 | J6: =H6*C6 -> 72 | K6: =H6*D6 -> 252 | L6: =H6*E6 -> 288 | M6: =H6*F6 -> 198 | N6: =H6*G6 -> 72
A7: Trouser | B7: 0 | C7: 0.08 | D7: 0.25 | E7: 0.32 | F7: 0.25 | G7: 0.1 | H7: 600 | I7: =H7*B7 -> 0 | J7: =H7*C7 -> 48 | K7: =H7*D7 -> 150 | L7: =H7*E7 -> 192 | M7: =H7*F7 -> 150 | N7: =H7*G7 -> 60
A8: Denim | B8: 0 | C8: 0.08 | D8: 0.25 | E8: 0.32 | F8: 0.25 | G8: 0.1 | H8: 500 | I8: =H8*B8 -> 0 | J8: =H8*C8 -> 40 | K8: =H8*D8 -> 125 | L8: =H8*E8 -> 160 | M8: =H8*F8 -> 125 | N8: =H8*G8 -> 50

Sheet Management Summary
A1: Management Summary
A4: Sales Target | B4: ='Project Brief'!B5 -> 100000000
A5: Gross Margin % | B5: ='Project Brief'!B6 -> 0.6
A6: Gross Margin ₹ | B6: =B4*B5 -> 60000000
A7: COGS ₹ | B7: =B4-B6 -> 40000000
A8: Opening Inventory ₹ | B8: ='Project Brief'!B7 -> 25000000
A9: Closing Inventory Target ₹ | B9: ='Project Brief'!B8 -> 30000000
A10: Illustrative Inventory Change ₹ | B10: =B9-B8 -> 5000000
A11: Management Observation | B11: Complete after reviewing the worksheets
A12: Action 1
A13: Action 2
A14: Action 3

Sheet Exercise Guide
A1: Exercise Guide
A3: Step | B3: Exercise | C3: What to do
A4: 1 | B4: Complete the Sales Plan | C4: Enter actual sales and analyse achievement and variance.
A5: 2 | B5: Complete Category Plan | C5: Review mix, ASP, units and stock allocation.
A6: 3 | B6: Complete 26-Week WSSI | C6: Enter actual sales/receipts and identify stock risks.
A7: 4 | B7: Complete OTB | C7: Enter actual orders and identify remaining OTB.
A8: 5 | B8: Analyse ROS/WOS | C8: Identify products needing action.
A9: 6 | B9: Build Assortment | C9: Review options, depth, price, colour and size mix.
A10: 7 | B10: Review Size Curve | C10: Adjust size percentages using your assumed customer demand.
A11: 8 | B11: Management Summary | C11: Write three commercial actions based on your analysis.
